[
  { "id": "refine", "group": "refine", "label": "Калькулятор", "ico": "⚒",
    "title": "Калькулятор заточки — PW Хелпер",
    "description": "Шанси, середня вартість і бюджет заточки спорядження Perfect World." },
  { "id": "simulator", "group": "refine", "label": "Симулятор", "ico": "◈",
    "title": "Симулятор заточки — PW Хелпер",
    "description": "Симулятор заточки Perfect World: спробуй удачу без витрат голди." },
  { "id": "eggs", "group": "shards", "label": "Вартість шарів", "ico": "◎",
    "title": "Вартість шарів — PW Хелпер",
    "description": "Розрахунок вартості шарів та каменів досконалості Perfect World." },
  { "id": "compare", "group": "shards", "label": "Порівняння", "ico": "⇌",
    "title": "Порівняння шарів — PW Хелпер",
    "description": "Порівняння способів добування шарів Perfect World: що вигідніше." },
  { "id": "craft", "group": "shards", "label": "Крафт шарів", "ico": "✦",
    "title": "Крафт шарів — PW Хелпер",
    "description": "Калькулятор крафту шарів Perfect World: складники та собівартість." },
  { "id": "r8", "group": "gear", "label": "Р8 бонуси", "ico": "🏆",
    "title": "Р8 бонуси — PW Хелпер",
    "description": "Бонуси спорядження Р8 Perfect World: сети, стати, порівняння." },
  { "id": "r8sim", "group": "gear", "label": "Симулятор Р8", "ico": "⚙",
    "title": "Симулятор Р8 — PW Хелпер",
    "description": "Симулятор ребонусу Р8 Perfect World: шанси на потрібні стати." },
  { "id": "gsn", "group": "gear", "label": "ГСН", "ico": "📿",
    "title": "ГСН — PW Хелпер",
    "description": "Калькулятор ГСН Perfect World: шанси та вартість спроб." },
  { "id": "abilities", "group": "gear", "label": "Абілки зброї", "ico": "⚔",
    "title": "Абілки зброї — PW Хелпер",
    "description": "Спец-абілки зброї Perfect World: назви, описи, шанси проків." },
  { "id": "doll", "group": "gear", "label": "Лялька", "ico": "🪆",
    "title": "Лялька персонажа — PW Хелпер",
    "description": "Лялька персонажа Perfect World: спорядження, камені, заточка, сети, бафи й повний розрахунок характеристик." },
  { "id": "skills", "group": "skillbase", "label": "Уміння класів", "ico": "✶",
    "title": "Уміння класів — PW Хелпер",
    "description": "Дерева вмінь усіх класів Perfect World з описами рівнів, Раю та Аду." },
  { "id": "genie", "group": "skillbase", "label": "Джинн", "ico": "🧞",
    "title": "Джинн: уміння та білд — PW Хелпер",
    "description": "Уміння джина Perfect World і калькулятор білда: рівень, удача, спорідненість." },
  { "id": "pets", "group": "skillbase", "label": "Питомець", "ico": "🐾",
    "title": "Уміння питомців — PW Хелпер",
    "description": "Уміння питомців Perfect World з описами та рівнями." },
  { "id": "chests", "label": "Скрині", "ico": "📦",
    "title": "Скрині — PW Хелпер",
    "description": "Симулятор скринь Perfect World: вміст, шанси, очікувана вартість." },
  { "id": "defense", "label": "Бій", "ico": "⚔",
    "title": "Бій і захист — PW Хелпер",
    "description": "Формули бою Perfect World: захист, % зрізання урону, рівні атаки." },
  { "id": "rb", "label": "РБ", "ico": "🐲",
    "title": "РБ — PW Хелпер",
    "description": "Помічник по РБ Perfect World: боси, чеклісти, мапи." },
  { "id": "guides", "label": "Гайди", "ico": "📖",
    "title": "Гайди — PW Хелпер",
    "description": "Гайди по Perfect World: фарм, розвиток, споти." },
  { "id": "settings", "label": "Налаштування", "ico": "⚙",
    "title": "Налаштування — PW Хелпер",
    "description": "Налаштування PW Хелпера: курс голди, ціни, тема." }
]
